mailparser_reply/__init__.py
mailparser_reply/constants.py
mailparser_reply/parser.py
mailparser_reply/version.py
mailparser_reply-1.0.dist-info/LICENSE
mailparser_reply-1.0.dist-info/METADATA
mailparser_reply-1.0.dist-info/WHEEL
mailparser_reply-1.0.dist-info/top_level.txt
mailparser_reply-1.0.dist-info/RECORD
